graphWriter/__init__.py
graphWriter/graphWriter.py
graphWriter-0.5.2.dist-info/LICENSE
graphWriter-0.5.2.dist-info/METADATA
graphWriter-0.5.2.dist-info/WHEEL
graphWriter-0.5.2.dist-info/top_level.txt
graphWriter-0.5.2.dist-info/RECORD
