Metadata-Version: 2.1
Name: graphWriter
Version: 0.5.2
Summary: A wrapper for TensorBoard SummaryWriter with real-time terminal visualization using the Rich library.
Home-page: https://github.com/COLVERTYETY/GraphWriter
Author: Nicolas STAS
Author-email: nicolas.jan.stas@gmail.com
License: UNKNOWN
Platform: UNKNOWN
Classifier: Programming Language :: Python :: 3
Classifier: License :: OSI Approved :: MIT License
Classifier: Operating System :: OS Independent
Classifier: Intended Audience :: Developers
Classifier: Topic :: Software Development :: Libraries :: Python Modules
Classifier: Topic :: Scientific/Engineering :: Visualization
Requires-Python: >=3.6
Requires-Dist: rich
Requires-Dist: asciichartpy
Requires-Dist: torch
Requires-Dist: tensorboard
